pycounts_abthuy/__init__.py
pycounts_abthuy/data/__init__.py
pycounts_abthuy/data/flatland.txt
pycounts_abthuy/datasets.py
pycounts_abthuy/plotting.py
pycounts_abthuy/pycounts.py
pycounts_abthuy-0.5.1.dist-info/LICENSE
pycounts_abthuy-0.5.1.dist-info/WHEEL
pycounts_abthuy-0.5.1.dist-info/METADATA
pycounts_abthuy-0.5.1.dist-info/RECORD
