Metadata-Version: 2.1
Name: pycounts-abthuy
Version: 0.5.1
Summary: Calculate word counts in a text file!
License: MIT
Author: Arthur Thuy
Requires-Python: >=3.9
Classifier: License :: OSI Approved :: MIT License
Classifier: Programming Language :: Python :: 3
Classifier: Programming Language :: Python :: 3.9
Classifier: Programming Language :: Python :: 3.10
Classifier: Programming Language :: Python :: 3.11
Requires-Dist: matplotlib (>=3.5.0)
